{
  "date": "Monday 8 June 2026",
  "subtitle": "Marie away all week, James absent until 18 June, multiple handovers to action",
  "context": "Marie Cooksey is on annual leave 8-12 June and James Salas Guillen is absent until Thursday 18 June - both handover documents are in your inbox and require immediate review. The DSE data import to Cardinus is now live (status confirmed by James on 5 June at 10:58) but Marie's question about manual contractor record creation remains unanswered and is blocking full sign-off. DTP1092 College Staff in PXD Proposal has multiple open comments from Marie and Simon Burford awaiting your review and closure. Michael O'Sullivan returned from leave this morning and has sent context on the Volunteering Days pilot. The most time-critical deadline this week is the Strategic H&S Modular System (SHSMS) weightings evaluation discussion with Helen Harbour - date not yet locked but marked urgent. Open first: the Marie Handover document to understand H&S queue coverage and which Marie-dependent items need independent action this week.",
  "urgent": [
    {
      "title": "Marie Handover 8-12 June",
      "sub": "<strong>Marie on leave all week.</strong> H&S coverage: Chris and Fire team have agreed support approach. Review handover document for all pending approvals and queue items that cannot wait.",
      "badge": "Review today",
      "badgeType": "red",
      "subject": "Marie Handover 8-12 June",
      "entry_id": "0000000060196AC9D4535F45A195B2716E93E76B0700FA1BE8B83D691D48B2219F82D0D3C4FB000000C7C97500008DFB9C6852DC5A43B72538034BBFF53500077C98646E0000"
    },
    {
      "title": "James Salas Guillen - Annual leave until 18 June",
      "sub": "<strong>Absent Friday 5 June through Thursday 18 June.</strong> H&S Handover, DSE data questions, and Cardinus archiving process all pending his input. Sharon and Rob listed as cover contacts.",
      "badge": "Handover review",
      "badgeType": "red",
      "subject": "Annual leave and support during my absence",
      "entry_id": "0000000060196AC9D4535F45A195B2716E93E76B0700FA1BE8B83D691D48B2219F82D0D3C4FB000000C7C97500008DFB9C6852DC5A43B72538034BBFF535000779BE36460000"
    },
    {
      "title": "DTP1092 - College Staff in PXD Proposal comments",
      "sub": "<strong>Multiple open comments from Marie and Simon require closure.</strong> Marie's questions on manual contractor record creation (from 5 June 11:36) remain unanswered and blocking sign-off. Simon has answered some comments; you replied on 4 June.",
      "badge": "Close comments",
      "badgeType": "red",
      "subject": "Marie Cooksey left a comment in \"DTP1092 - College Staff in PXD Proposal\"",
      "entry_id": "0000000060196AC9D4535F45A195B2716E93E76B0700FA1BE8B83D691D48B2219F82D0D3C4FB000000C7C97500008DFB9C6852DC5A43B72538034BBFF535000779BE36260000"
    }
  ],
  "needs": [
    {
      "title": "H&S Handover - James Salas Guillen",
      "sub": "Detailed handover document with current outstanding items. Review before James leaves to understand coverage gaps and any escalations needed during his 18 June return date.",
      "badge": "By 18 June",
      "badgeType": "yellow",
      "subject": "H&S Handover",
      "entry_id": "0000000060196AC9D4535F45A195B2716E93E76B0700FA1BE8B83D691D48B2219F82D0D3C4FB000000C7C97500008DFB9C6852DC5A43B72538034BBFF535000779BE36480000"
    },
    {
      "title": "DSE Update - PeopleXD to Cardinus interface",
      "sub": "James confirmed interface is live (5 June 10:58). Marie asked about manual contractor records on 5 June 11:36 - answer required before process is fully live. James's departure 5 June-18 June means questions may need escalation.",
      "badge": "Confirm coverage",
      "badgeType": "yellow",
      "subject": "RE: DSE Update - user data import and upload to Cardinus",
      "entry_id": "0000000060196AC9D4535F45A195B2716E93E76B0700FA1BE8B83D691D48B2219F82D0D3C4FB000000C7C97500008DFB9C6852DC5A43B72538034BBFF535000779BE363A0000"
    },
    {
      "title": "Preventing archiving of users not included in HR data upload",
      "sub": "James sent detailed technical update on 5 June on automated PeopleXD data upload to DSE (Healthy Working Plus). Review implications for user archiving policy.",
      "badge": "Within 48 hours",
      "badgeType": "yellow",
      "subject": "FW: Preventing archiving of users not included in HR data upload",
      "entry_id": "0000000060196AC9D4535F45A195B2716E93E76B0700FA1BE8B83D691D48B2219F82D0D3C4FB000000C7C97500008DFB9C6852DC5A43B72538034BBFF535000779BE36470000"
    },
    {
      "title": "Strategic H&S Modular System (SHSMS) weightings evaluation",
      "sub": "Helen Harbour sent invitation to discuss proposed evaluation criteria weightings. Documentation to follow. Schedule slot and review weightings document when received.",
      "badge": "Schedule meeting",
      "badgeType": "yellow",
      "subject": "Strategic H&S Modular System requirements evaluation weightings",
      "entry_id": "0000000060196AC9D4535F45A195B2716E93E76B0700FA1BE8B83D691D48B2219F82D0D3C4FB000000C7C97500008DFB9C6852DC5A43B72538034BBFF535000779BE36420000"
    },
    {
      "title": "Access Support case 68981549 resolved",
      "sub": "Case marked resolved 5 June at 16:42. Confirm closure or reopen if further action needed.",
      "badge": "Confirm closure",
      "badgeType": "yellow",
      "subject": "Access Support Team | 68981549 - Your Case Has Been Resolved",
      "entry_id": "0000000060196AC9D4535F45A195B2716E93E76B0700FA1BE8B83D691D48B2219F82D0D3C4FB000000C7C97500008DFB9C6852DC5A43B72538034BBFF535000779BE364B0000"
    }
  ],
  "fyi": [
    {
      "title": "Michael O'Sullivan - back from leave",
      "sub": "Returned 8 June morning with context on Volunteering Days pilot. Calendar meeting 1-1 session accepted.",
      "badge": "Context noted",
      "badgeType": "blue",
      "subject": "RE: Question re Volunteer reporting",
      "entry_id": "0000000060196AC9D4535F45A195B2716E93E76B0700FA1BE8B83D691D48B2219F82D0D3C4FB000000C7C97500008DFB9C6852DC5A43B72538034BBFF53500077D9F1E200000"
    },
    {
      "title": "CorityOne Maintenance completed",
      "sub": "GX2 TEST Release 2026.2 maintenance completed 6 June 19:00. No components affected.",
      "badge": "Completed",
      "badgeType": "blue",
      "subject": "CorityOne Maintenance - GX2 - TEST Release 2026.2 - 6 June 2026",
      "entry_id": "0000000060196AC9D4535F45A195B2716E93E76B0700FA1BE8B83D691D48B2219F82D0D3C4FB000000C7C97500008DFB9C6852DC5A43B72538034BBFF53500077C76F7B60000"
    },
    {
      "title": "OWL Network Maintenance - 11 June",
      "sub": "James Turner: captive portal upgrade scheduled for 11 June. Monitor for user impact.",
      "badge": "11 June",
      "badgeType": "blue",
      "subject": "[ict-a] OWL Maintenance - 11th June",
      "entry_id": "0000000060196AC9D4535F45A195B2716E93E76B0700FA1BE8B83D691D48B2219F82D0D3C4FB000000C7C97500008DFB9C6852DC5A43B72538034BBFF535000779BE36430000"
    },
    {
      "title": "Citory GX2 2026.2 Release",
      "sub": "New release with refreshed navigation and AI features now available. Review release notes.",
      "badge": "Available",
      "badgeType": "blue",
      "subject": "Your GX2 2026.2 Release is Here with Refreshed Navigation and Smarter AI",
      "entry_id": "0000000060196AC9D4535F45A195B2716E93E76B0700FA1BE8B83D691D48B2219F82D0D3C4FB000000C7C97500008DFB9C6852DC5A43B72538034BBFF535000779BE362F0000"
    },
    {
      "title": "Cority Product User Group (PUG)",
      "sub": "Christopher Sanders meeting invite. Agenda to follow.",
      "badge": "Pending agenda",
      "badgeType": "blue",
      "subject": "Cority Product User Group (PUG)",
      "entry_id": "0000000060196AC9D4535F45A195B2716E93E76B0700FA1BE8B83D691D48B2219F82D0D3C4FB000000C7C97500008DFB9C6852DC5A43B72538034BBFF535000779BE36440000"
    },
    {
      "title": "POC for HALO data work",
      "sub": "Simon Burford forwarded query from Daphne regarding HALO data work POC. Context to follow in conversation.",
      "badge": "FYI",
      "badgeType": "blue",
      "subject": "FW: POC for HALO data work?",
      "entry_id": "0000000060196AC9D4535F45A195B2716E93E76B0700FA1BE8B83D691D48B2219F82D0D3C4FB000000C7C97500008DFB9C6852DC5A43B72538034BBFF535000779BE36350000"
    },
    {
      "title": "GLAM Rostering discussion",
      "sub": "Simon Burford: Marie asked to discuss Botanic Gardens setup on Rostering following approval.",
      "badge": "Pending",
      "badgeType": "blue",
      "subject": "GLAM Rostering",
      "entry_id": "0000000060196AC9D4535F45A195B2716E93E76B0700FA1BE8B83D691D48B2219F82D0D3C4FB000000C7C97500008DFB9C6852DC5A43B72538034BBFF535000779BE36310000"
    },
    {
      "title": "Marie Cooksey Kudoboard finalized",
      "sub": "Last call for contributions to farewell Kudoboard before finalization.",
      "badge": "Deadline soon",
      "badgeType": "blue",
      "subject": "The Kudoboard for Marie Cooksey is being finalized",
      "entry_id": "0000000060196AC9D4535F45A195B2716E93E76B0700FA1BE8B83D691D48B2219F82D0D3C4FB000000C7C97500008DFB9C6852DC5A43B72538034BBFF535000779BE36410000"
    },
    {
      "title": "Pay Uplift Staff Team added",
      "sub": "Jessica Oldershaw added you to Pay Uplift Staff team. 18 members coordinating pay uplift work.",
      "badge": "Team added",
      "badgeType": "blue",
      "subject": "You have been added to a staff team in Microsoft Teams",
      "entry_id": "0000000060196AC9D4535F45A195B2716E93E76B0700FA1BE8B83D691D48B2219F82D0D3C4FB000000C7C97500008DFB9C6852DC5A43B72538034BBFF535000779BE36320000"
    },
    {
      "title": "Clinical pay uplift 2026 kick off",
      "sub": "Jasmin Khokhra: kick off meeting scheduled early due to tight timeline.",
      "badge": "Noted",
      "badgeType": "blue",
      "subject": "Clinical pay uplift 2026 kick off meeting",
      "entry_id": "0000000060196AC9D4535F45A195B2716E93E76B0700FA1BE8B83D691D48B2219F82D0D3C4FB000000C7C97500008DFB9C6852DC5A43B72538034BBFF535000779BE363B0000"
    }
  ],
  "low": [
    {
      "title": "New Vacancy Notifications",
      "sub": "Job board updates matching your criteria. Two notifications sent 5-6 June.",
      "badge": "Admin",
      "badgeType": "gray",
      "subject": "New Vacancy Notification",
      "entry_id": "0000000060196AC9D4535F45A195B2716E93E76B0700FA1BE8B83D691D48B2219F82D0D3C4FB000000C7C97500008DFB9C6852DC5A43B72538034BBFF535000779BE36380000"
    },
    {
      "title": "Access Support case feedback surveys",
      "sub": "Feedback survey requests from The Access Group (2 items, 4-5 June).",
      "badge": "Optional",
      "badgeType": "gray",
      "subject": "Access Support - Case Feedback"
    },
    {
      "title": "Cority Customer Support note option",
      "sub": "Response to James re draft notes functionality in Cority. Reference 00476764.",
      "badge": "Support Q&A",
      "badgeType": "gray",
      "subject": "Option to draft or come back to a note after 'saving' [ ref:_00DE0JBMl._500OFR5uTZ:ref ] 00476764.",
      "entry_id": "0000000060196AC9D4535F45A195B2716E93E76B0700FA1BE8B83D691D48B2219F82D0D3C4FB000000C7C97500008DFB9C6852DC5A43B72538034BBFF535000779BE36280000"
    },
    {
      "title": "Digital Capabilities training courses",
      "sub": "Courses offered in weeks 7-8: Word, LaTeX, Planner, MS Projects, summer refresh toolkit.",
      "badge": "Optional",
      "badgeType": "gray",
      "subject": "A Summer Refresh for Your Digital Toolkit in Weeks 7 & 8",
      "entry_id": "0000000060196AC9D4535F45A195B2716E93E76B0700FA1BE8B83D691D48B2219F82D0D3C4FB000000C7C97500008DFB9C6852DC5A43B72538034BBFF535000779BE363F0000"
    },
    {
      "title": "ICTF Conference 2026 registration closed",
      "sub": "Registration deadline was 5 June 17:30. Conference details available.",
      "badge": "Closed",
      "badgeType": "gray",
      "subject": "[ict-a] ICTF Conference 2026 - Final Week for Registration"
    },
    {
      "title": "Cisco VPN update completed",
      "sub": "Philip White: Cisco Secure Client update to 5.1.17.3394 completed successfully.",
      "badge": "Completed",
      "badgeType": "gray",
      "subject": "RE: [ict-a] Cisco Secure Client (VPN) update to 5.1.17.3394",
      "entry_id": "0000000060196AC9D4535F45A195B2716E93E76B0700FA1BE8B83D691D48B2219F82D0D3C4FB000000C7C97500008DFB9C6852DC5A43B72538034BBFF535000779BE36400000"
    },
    {
      "title": "Training industry trends reminder",
      "sub": "AccessPlanit reminder: Training Industry Benchmark Report 2026.",
      "badge": "Reminder",
      "badgeType": "gray",
      "subject": "Reminder: Training industry trends 2026 - Insights from the Training Industry Benchmark Report",
      "entry_id": "0000000060196AC9D4535F45A195B2716E93E76B0700FA1BE8B83D691D48B2219F82D0D3C4FB000000C7C97500008DFB9C6852DC5A43B72538034BBFF535000779BE36240000"
    },
    {
      "title": "ElevenLabs login notification",
      "sub": "New login detected from Edge on Windows. Verify if you initiated.",
      "badge": "Security check",
      "badgeType": "gray",
      "subject": "New login from Edge on Windows",
      "entry_id": "0000000060196AC9D4535F45A195B2716E93E76B0700FA1BE8B83D691D48B2219F82D0D3C4FB000000C7C97500008DFB9C6852DC5A43B72538034BBFF535000779BE36230000"
    },
    {
      "title": "Wispr Flow May recap",
      "sub": "Monthly productivity stats and highlights.",
      "badge": "Info",
      "badgeType": "gray",
      "subject": "Your May Flow State recap",
      "entry_id": "0000000060196AC9D4535F45A195B2716E93E76B0700FA1BE8B83D691D48B2219F82D0D3C4FB000000C7C97500008DFB9C6852DC5A43B72538034BBFF53500077C9864700000"
    },
    {
      "title": "Cority Employee Import error - 2026-06-05",
      "sub": "Error in HR data import from PeopleXD to Cority OxfordUniversity_Demo. Log file attached. Review with IT.",
      "badge": "IT issue",
      "badgeType": "gray",
      "subject": "[ERROR] Cority Employee Import Log File for OxfordUniversity_Demo - 2026-06-05 23:00",
      "entry_id": "0000000060196AC9D4535F45A195B2716E93E76B0700FA1BE8B83D691D48B2219F82D0D3C4FB000000C7C97500008DFB9C6852DC5A43B72538034BBFF53500077C2ACCC80000"
    }
  ],
  "calToday": [
    {
      "time": "09:30",
      "title": "Meeting - FA Team Daily Catchup",
      "sub": "Microsoft Teams Meeting",
      "alert": ""
    },
    {
      "time": "10:00",
      "title": "Meeting - H&S Roadmap",
      "sub": "Christopher Sanders organizer. Regular catch-up on open support tickets, H&S roadmap and backlog items.",
      "alert": ""
    },
    {
      "time": "11:00",
      "title": "Meeting - Simon / Kevin 121s",
      "sub": "Simon Burford: weekly catch-up (moving to fortnightly when you are settled)",
      "alert": ""
    },
    {
      "time": "13:00",
      "title": "Blocked - Busy",
      "sub": "13:00-17:00 blocked for priority work",
      "alert": ""
    }
  ],
  "calTomorrow": [
    {
      "time": "09:30",
      "title": "Meeting - FA Team Daily Catchup",
      "sub": "Microsoft Teams Meeting",
      "alert": ""
    },
    {
      "time": "13:00",
      "title": "Blocked - Busy",
      "sub": "13:00-17:00 blocked for priority work",
      "alert": ""
    }
  ],
  "absences": [
    "Marie Cooksey - annual leave 8-12 June",
    "James Salas Guillen - annual leave 5-18 June"
  ],
  "priorities": [
    {
      "text": "Review Marie Handover document and identify H&S queue items requiring independent action during her 8-12 June absence",
      "date": "8 June",
      "dateType": "red",
      "subject": "Marie Handover 8-12 June",
      "entry_id": "0000000060196AC9D4535F45A195B2716E93E76B0700FA1BE8B83D691D48B2219F82D0D3C4FB000000C7C97500008DFB9C6852DC5A43B72538034BBFF53500077C98646E0000"
    },
    {
      "text": "Close open comments on DTP1092 proposal - answer Marie's 5 June question about manual contractor record creation in Cardinus",
      "date": "8 June",
      "dateType": "red",
      "subject": "Marie Cooksey left a comment in \"DTP1092 - College Staff in PXD Proposal\"",
      "entry_id": "0000000060196AC9D4535F45A195B2716E93E76B0700FA1BE8B83D691D48B2219F82D0D3C4FB000000C7C97500008DFB9C6852DC5A43B72538034BBFF535000779BE36260000"
    },
    {
      "text": "Review James Salas Guillen H&S Handover document and confirm coverage arrangements for his 5-18 June absence",
      "date": "8 June",
      "dateType": "red",
      "subject": "H&S Handover",
      "entry_id": "0000000060196AC9D4535F45A195B2716E93E76B0700FA1BE8B83D691D48B2219F82D0D3C4FB000000C7C97500008DFB9C6852DC5A43B72538034BBFF535000779BE36480000"
    },
    {
      "text": "Schedule SHSMS weightings evaluation meeting with Helen Harbour and review criteria documentation when received",
      "date": "8-9 June",
      "dateType": "yellow",
      "subject": "Strategic H&S Modular System requirements evaluation weightings",
      "entry_id": "0000000060196AC9D4535F45A195B2716E93E76B0700FA1BE8B83D691D48B2219F82D0D3C4FB000000C7C97500008DFB9C6852DC5A43B72538034BBFF535000779BE36420000"
    },
    {
      "text": "Confirm resolution of Access Support case 68981549 or reopen if further investigation required",
      "date": "9 June",
      "dateType": "yellow",
      "subject": "Access Support Team | 68981549 - Your Case Has Been Resolved",
      "entry_id": "0000000060196AC9D4535F45A195B2716E93E76B0700FA1BE8B83D691D48B2219F82D0D3C4FB000000C7C97500008DFB9C6852DC5A43B72538034BBFF535000779BE364B0000"
    }
  ],
  "refreshed_at": "Monday 08 June · 09:15"
}